brylic-0.1.0.dist-info/METADATA
brylic-0.1.0.dist-info/WHEEL
brylic-0.1.0.dist-info/licenses/LICENSE_rlic
brylic-0.1.0.dist-info/licenses/LICENSE_vectorplot
brylic.libs/libgcc_s-6d2d9dc8.so.1
brylic/__init__.py
brylic/_boundaries.py
brylic/_core.abi3.so
brylic/_core.pyi
brylic/_lib.py
brylic/_typing.py
brylic/py.typed
brylic-0.1.0.dist-info/RECORD
